pycolorterm
