Metadata-Version: 1.0
Name: pycolorterm
Version: 0.1.2
Summary: PyColorTerm allows you to write colored and styled lines out in the terminal from Python and in a pythonic way
Home-page: https://github.com/dnmellen/pycolorterm
Author: Diego Navarro Mellén
Author-email: dnmellen@gmail.com
License: BSD
Keywords: pycolorterm
Platform: UNKNOWN
Classifier: Development Status :: 2 - Pre-Alpha
Classifier: Intended Audience :: Developers
Classifier: License :: OSI Approved :: BSD License
Classifier: Natural Language :: English
Classifier: Programming Language :: Python :: 2
Classifier: Programming Language :: Python :: 2.6
Classifier: Programming Language :: Python :: 2.7
Classifier: Programming Language :: Python :: 3
Classifier: Programming Language :: Python :: 3.3
